packageitstructureexample/bar/__init__.py
packageitstructureexample/bar/__main__.py
packageitstructureexample/bar/bar.ini
packageitstructureexample/foo/__init__.py
PackageItStructureExample-0.0.12.dist-info/LICENSE
PackageItStructureExample-0.0.12.dist-info/METADATA
PackageItStructureExample-0.0.12.dist-info/WHEEL
PackageItStructureExample-0.0.12.dist-info/entry_points.txt
PackageItStructureExample-0.0.12.dist-info/top_level.txt
PackageItStructureExample-0.0.12.dist-info/RECORD
