Metadata-Version: 2.1
Name: PackageItStructureExample
Version: 0.0.12
Summary: Insert project description here
Author: Hendrik du Toit
Author-email: hendrik@brightedge.co.za
License: UNKNOWN
Platform: UNKNOWN
Classifier: Development Status :: 1 - Planning
Classifier: Intended Audience :: Developers
Classifier: Topic :: Software Development
Classifier: License :: OSI Approved :: MIT License
Classifier: Programming Language :: Python :: 3.9
Classifier: Programming Language :: Python :: 3.10
License-File: LICENSE
Requires-Dist: beetools
Requires-Dist: configparserext
Requires-Dist: releaselogit
Requires-Dist: semverit
Requires-Dist: termcolor
Requires-Dist: toml
